{
    "spriteSheetURL": "./graphics/Elementals_metal_bladekeeper/metal_bladekeeper_FREE.png",
    "type":"none",
    "size":[288,128],
    "sprites":[

        {
            "name":"bladekeeper_1_BS2",
            "x":0,
            "y":1536,
            "scalefactor":3,
            "colorKey":-1
        },
        {
            "name":"bladekeeper_2_BS2",
            "x":288,
            "y":1536,
            "scalefactor":3,
            "colorKey":-1
        },
        {
            "name":"bladekeeper_3_BS2",
            "x":576,
            "y":1536,
            "scalefactor":3,
            "colorKey":-1
        },
		{
            "name":"bladekeeper_4_BS2",
            "x":864,
            "y":1536,
            "scalefactor":3,
            "colorKey":-1
        },
        {
            "name":"bladekeeper_5_BS2",
            "x":1152,
            "y":1536,
            "scalefactor":3,
            "colorKey":-1
        },
        {
            "name":"bladekeeper_6_BS2",
            "x":1440,
            "y":1536,
            "scalefactor":3,
            "colorKey":-1
        },
        {
            "name":"bladekeeper_7_BS2",
            "x":1728,
            "y":1536,
            "scalefactor":3,
            "colorKey":-1
        },
		{
            "name":"bladekeeper_8_BS2",
            "x":2016,
            "y":1536,
            "scalefactor":3,
            "colorKey":-1
        },
        {
            "name":"bladekeeper_9_BS2",
            "x":2304,
            "y":1536,
            "scalefactor":3,
            "colorKey":-1
        },
        {
            "name":"bladekeeper_10_BS2",
            "x":2592,
            "y":1536,
            "scalefactor":3,
            "colorKey":-1
        },
		{
            "name":"bladekeeper_11_BS2",
            "x":2880,
            "y":1536,
            "scalefactor":3,
            "colorKey":-1
        }
    ]
}