{
    "spriteSheetURL": "./graphics/Fire_Sprite.png",
    "type":"none",
    "size":[256,256],
    "sprites":[
        {
            "name":"flame_1",
            "x":0,
            "y":0,
            "scalefactor":10,
            "colorKey":-1
	   },
        {
            "name":"flame_2",
            "x":256,
            "y":0,
            "scalefactor":10,
            "colorKey":-1
        },
        {
            "name":"flame_3",
            "x":513,
            "y":0,
            "scalefactor":10,
            "colorKey":-1
        },
        {
            "name":"flame_4",
            "x":0,
            "y":256,
            "scalefactor":10,
            "colorKey":-1
        },
        {
            "name":"flame_5",
            "x":256,
            "y":256,
            "scalefactor":10,
            "colorKey":-1
        },
        {
            "name":"flame_6",
            "x":513,
            "y":256,
            "scalefactor":10,
            "colorKey":-1
        },
        {
            "name":"flame_7",
            "x":0,
            "y":513,
            "scalefactor":10,
            "colorKey":-1
        },
        {
            "name":"flame_8",
            "x":256,
            "y":513,
            "scalefactor":10,
            "colorKey":-1
        },
        {
            "name":"flame_9",
            "x":513,
            "y":513,
            "scalefactor":10,
            "colorKey":-1
        }
    ]
}